cobrafuzz/__init__.py
cobrafuzz/common.py
cobrafuzz/fuzzer.py
cobrafuzz/main.py
cobrafuzz/mutator.py
cobrafuzz/prune.py
cobrafuzz/py.typed
cobrafuzz/simplifier.py
cobrafuzz/state.py
cobrafuzz/tracer.py
cobrafuzz/util.py
stubs/__init__.pyi
stubs/scipy/__init__.pyi
stubs/scipy/stats.pyi
tests/__init__.py
tests/test_doc.py
tests/utils.py
cobrafuzz-2.3.0.dist-info/LICENSE
cobrafuzz-2.3.0.dist-info/METADATA
cobrafuzz-2.3.0.dist-info/WHEEL
cobrafuzz-2.3.0.dist-info/top_level.txt
cobrafuzz-2.3.0.dist-info/RECORD
