Metadata-Version: 2.1
Name: cobrafuzz
Version: 2.3.0
Summary: Coverage-guided fuzz testing for Python
Author-email: Alexander Senier <mail@senier.net>
Classifier: Programming Language :: Python :: 3
Classifier: License :: OSI Approved :: Apache Software License
Classifier: Operating System :: OS Independent
Classifier: Topic :: Software Development :: Testing
Requires-Python: >=3.8.0
License-File: LICENSE
Requires-Dist: dill ==0.3.8
Provides-Extra: devel
Requires-Dist: black ==23.12.1 ; extra == 'devel'
Requires-Dist: beautifulsoup4 ==4.12.3 ; extra == 'devel'
Requires-Dist: build ==1.0.3 ; extra == 'devel'
Requires-Dist: charset-normalizer ==3.3.2 ; extra == 'devel'
Requires-Dist: furl ==2.1.3 ; extra == 'devel'
Requires-Dist: idna ==3.6 ; extra == 'devel'
Requires-Dist: isort ==5.13.2 ; extra == 'devel'
Requires-Dist: mypy <1.8.0 ; extra == 'devel'
Requires-Dist: plotly ==5.19.0 ; extra == 'devel'
Requires-Dist: purl ==1.6 ; extra == 'devel'
Requires-Dist: pytest ==7.4.4 ; extra == 'devel'
Requires-Dist: pytest-cov ==4.1.0 ; extra == 'devel'
Requires-Dist: pytest-xdist ==3.5.0 ; extra == 'devel'
Requires-Dist: python-dateutil ==2.9.0 ; extra == 'devel'
Requires-Dist: python-kacl ==0.4.6 ; extra == 'devel'
Requires-Dist: requests ==2.31.0 ; extra == 'devel'
Requires-Dist: ruff ==0.1.13 ; extra == 'devel'
Requires-Dist: types-requests ==2.31.0.20240125 ; extra == 'devel'
Requires-Dist: vulture ==2.11 ; extra == 'devel'
Requires-Dist: scipy <1.11 ; (python_version < "3.9") and extra == 'devel'
Requires-Dist: scipy ==1.11.4 ; (python_version >= "3.9") and extra == 'devel'
Provides-Extra: extra-devel
Requires-Dist: recordflux ==0.18.0 ; extra == 'extra-devel'
